numchest/__init__.py
numchest/roots.py
numchest/tabular.py
numchest-0.0.4.dist-info/LICENSE
numchest-0.0.4.dist-info/METADATA
numchest-0.0.4.dist-info/WHEEL
numchest-0.0.4.dist-info/top_level.txt
numchest-0.0.4.dist-info/RECORD
