Metadata-Version: 2.1
Name: numchest
Version: 0.0.4
Summary: A little treasure chest of numerical utility functions
Home-page: https://github.com/holgerschmitz/numchest
Author: Holger Schmitz
Author-email: holger@notjustphysics.com
License: UNKNOWN
Project-URL: Bug Tracker, https://github.com/holgerschmitz/numchest/issues
Platform: UNKNOWN
Classifier: Programming Language :: Python :: 3
Classifier: License :: OSI Approved :: MIT License
Classifier: Operating System :: OS Independent
Requires-Python: >=3.6
License-File: LICENSE
